{
  "sourceUrl": "https://adroll.com/",
  "name": "AdRoll",
  "title": "adroll.com",
  "payoff": "Simplify your digital ad campaigns",
  "shortDescription": "AdRoll is a marketing platform designed for brands and agencies to optimize digital advertising efforts across multiple channels. It integrates with major e-commerce and advertising platforms like Shopify, Google Ads, and Meta, enabling users to manage campaigns effectively. Example use case: An e-commerce store uses AdRoll to re-engage visitors who abandoned their shopping carts, increasing conversions.",
  "pros": [
    "Integrates with major e-commerce platforms",
    "Supports a wide range of advertising channels",
    "Offers retargeting and audience targeting features"
  ],
  "cons": [
    "May be complex for beginners",
    "Potentially high cost for small businesses",
    "Limited customization in certain areas"
  ],
  "alternatives": [
    "Criteo [criteo.com]",
    "Google Ads [ads.google.com]",
    "Facebook Ads [facebook.com/business/ads]"
  ],
  "aiSuggestedAlternatives": [
    {
      "name": "Criteo",
      "url": "criteo.com",
      "reason": "Strong in dynamic retargeting ads"
    },
    {
      "name": "Google Ads",
      "url": "ads.google.com",
      "reason": "Extensive reach and detailed analytics"
    },
    {
      "name": "Facebook Ads",
      "url": "facebook.com/business/ads",
      "reason": "Excellent for social media targeting"
    }
  ],
  "tags": [
    "marketing tools",
    "advertising",
    "programmatic advertising",
    "campaign management"
  ],
  "apiUsed": true,
  "department": "Marketing",
  "function": "Marketing Tools",
  "freeTier": true,
  "openSource": false,
  "releasedYear": 2007,
  "websiteUrl": "https://adroll.com/",
  "documentationUrl": "https://help.adroll.com",
  "githubUrl": "https://github.com/search?q=adroll&type=repositories",
  "twitterUrl": "https://twitter.com/AdRoll",
  "screenshot": "https://share.appsfor.us/screenshots/adroll_com.png",
  "screenshot_640": "https://share.appsfor.us/screenshots/adroll_com_640.png",
  "screenshot_400": "https://share.appsfor.us/screenshots/adroll_com_400.png",
  "updatedAt": "2025-05-24T10:05:45.413Z"
}