{
  "sourceUrl": "https://codemate.ai/",
  "name": "CodeMate",
  "title": "codemate.ai",
  "payoff": "AI Pair Programmer for Developers",
  "shortDescription": "CodeMate is an AI-driven coding assistant designed to enhance the productivity of developers. It offers features like AI-powered autocompletions, code reviews, and debugging across various IDEs. Ideal for both individual developers and teams, CodeMate helps in generating full-stack applications, managing documentation, and integrating seamlessly with existing environments. An example use case is a developer using CodeMate to refactor code and generate unit tests efficiently.",
  "pros": [
    "Enhances coding productivity with AI",
    "Supports full-stack application generation",
    "Integrates with existing development environments"
  ],
  "cons": [
    "May not support all programming languages",
    "Potential learning curve for new users",
    "Dependence on AI accuracy for critical tasks"
  ],
  "alternatives": [
    "Kite [kite.com]",
    "GitHub Copilot [copilot.github.com]",
    "Tabnine [tabnine.com]"
  ],
  "aiSuggestedAlternatives": [
    {
      "name": "Kite",
      "url": "kite.com",
      "reason": "Offers AI-powered code completions"
    },
    {
      "name": "GitHub Copilot",
      "url": "copilot.github.com",
      "reason": "AI pair programmer by GitHub"
    },
    {
      "name": "Tabnine",
      "url": "tabnine.com",
      "reason": "Code completion tool using AI"
    }
  ],
  "tags": [
    "AI",
    "development",
    "productivity",
    "code assistance"
  ],
  "apiUsed": true,
  "department": "Development",
  "function": "Development",
  "freeTier": false,
  "openSource": false,
  "releasedYear": 2020,
  "websiteUrl": "https://codemate.ai/",
  "documentationUrl": "https://codemate.ai/docs",
  "githubUrl": "https://github.com/search?q=codemate&type=repositories",
  "twitterUrl": "https://twitter.com/codemateai",
  "screenshot": "https://share.appsfor.us/screenshots/codemate_ai.png",
  "screenshot_640": "https://share.appsfor.us/screenshots/codemate_ai_640.png",
  "screenshot_400": "https://share.appsfor.us/screenshots/codemate_ai_400.png",
  "updatedAt": "2025-05-24T11:25:20.828Z"
}