{
  "sourceUrl": "https://getcartwheel.com/",
  "name": "Cartwheel",
  "title": "getcartwheel.com",
  "payoff": "Animate simply by typing",
  "shortDescription": "Cartwheel is a text-to-animation platform designed to simplify the creation of animations for various digital projects. Users can animate characters for videos, games, apps, advertisements, and social or virtual reality projects just by typing. This tool is ideal for developers, designers, and content creators who need quick and customizable animations. An example use case could be a game developer creating character animations without needing complex animation software.",
  "pros": [
    "Easy text-to-animation conversion",
    "Editable animations for customization",
    "Supports a wide range of digital projects"
  ],
  "cons": [
    "May require learning for best results",
    "Limited to the styles and characters provided",
    "Potential dependency on platform updates"
  ],
  "alternatives": [
    "Adobe Character Animator [adobe.com]",
    "Toonly [toonly.com]",
    "Animaker [animaker.com]"
  ],
  "aiSuggestedAlternatives": [
    {
      "name": "Adobe Character Animator",
      "url": "adobe.com",
      "reason": "Offers live motion capture & animation"
    },
    {
      "name": "Toonly",
      "url": "toonly.com",
      "reason": "Simple drag-and-drop animation tool"
    },
    {
      "name": "Animaker",
      "url": "animaker.com",
      "reason": "Offers DIY video animation with assets"
    }
  ],
  "tags": [
    "animation",
    "text-to-animation",
    "video production",
    "virtual reality"
  ],
  "apiUsed": false,
  "department": "Creative",
  "function": "Design Tools",
  "freeTier": false,
  "openSource": false,
  "releasedYear": 2021,
  "websiteUrl": "https://getcartwheel.com/",
  "documentationUrl": "https://docs.getcartwheel.com/",
  "githubUrl": "https://github.com/search?q=cartwheel&type=repositories",
  "twitterUrl": null,
  "screenshot": "/screenshots/getcartwheel_com.png",
  "screenshot_640": "/screenshots/getcartwheel_com_640.png",
  "screenshot_400": "/screenshots/getcartwheel_com_400.png",
  "updatedAt": "2025-05-14T06:49:45.442Z"
}