{
  "sourceUrl": "https://kumo.ai/",
  "name": "Kumo",
  "title": "kumo.ai",
  "payoff": "AI for relational enterprise data",
  "shortDescription": "Kumo leverages AI to provide instant predictive insights from relational enterprise data, without the need for machine learning pipelines or extensive setup. It is designed for business users who can interact with the system using natural language to get reliable, explainable answers. An example use case includes enhancing operational efficiency and personalized shopping experiences in retail.",
  "pros": [
    "Instant predictions with zero setup",
    "No ML experience required",
    "Natural language interaction"
  ],
  "cons": [
    "Limited to relational data",
    "May require fine-tuning for complex queries",
    "Dependent on data quality and structure"
  ],
  "alternatives": [
    "DataRobot [datarobot.com]",
    "H2O.ai [h2o.ai]",
    "RapidMiner [rapidminer.com]"
  ],
  "aiSuggestedAlternatives": [
    {
      "name": "DataRobot",
      "url": "datarobot.com",
      "reason": "Offers automated machine learning"
    },
    {
      "name": "H2O.ai",
      "url": "h2o.ai",
      "reason": "Focuses on open-source ML tools"
    },
    {
      "name": "RapidMiner",
      "url": "rapidminer.com",
      "reason": "Provides a visual workflow for ML"
    }
  ],
  "tags": [
    "AI",
    "predictive analytics",
    "data analytics",
    "enterprise"
  ],
  "apiUsed": false,
  "department": "Data & Analytics",
  "function": "AI & ML",
  "freeTier": false,
  "openSource": false,
  "releasedYear": 2021,
  "websiteUrl": "https://kumo.ai/",
  "documentationUrl": null,
  "githubUrl": "https://github.com/search?q=kumo&type=repositories",
  "twitterUrl": null,
  "screenshot": "https://share.appsfor.us/screenshots/kumo_ai.png",
  "screenshot_640": "https://share.appsfor.us/screenshots/kumo_ai_640.png",
  "screenshot_400": "https://share.appsfor.us/screenshots/kumo_ai_400.png",
  "updatedAt": "2025-06-01T01:22:11.625Z"
}