{
  "sourceUrl": "https://linktr.ee/",
  "name": "Linktree",
  "title": "linktr.ee",
  "payoff": "One link to share everything",
  "shortDescription": "Linktree allows users to consolidate all their digital content under one link, ideal for sharing on social media bios like Instagram and Twitter. Users can connect various content types such as websites, stores, videos, and more. This tool is particularly useful for influencers, marketers, and businesses looking to streamline their online presence and enhance audience engagement through a single, customizable link.",
  "pros": [
    "Easy to set up and manage",
    "Supports various content types",
    "Provides detailed analytics"
  ],
  "cons": [
    "Limited design customization",
    "Dependent on platform stability",
    "Potential privacy concerns with data tracking"
  ],
  "alternatives": [
    "Bio.fm [bio.fm]",
    "Campsite [campsite.bio]",
    "Taplink [taplink.cc]"
  ],
  "aiSuggestedAlternatives": [
    {
      "name": "Bio.fm",
      "url": "bio.fm",
      "reason": "Offers similar link consolidation"
    },
    {
      "name": "Campsite",
      "url": "campsite.bio",
      "reason": "Customizable bio link tool"
    },
    {
      "name": "Taplink",
      "url": "taplink.cc",
      "reason": "Adds commerce features to links"
    }
  ],
  "tags": [
    "link management",
    "social media tool",
    "content sharing",
    "audience engagement"
  ],
  "apiUsed": false,
  "department": "Marketing",
  "function": "Link Tools",
  "freeTier": true,
  "openSource": false,
  "releasedYear": 2016,
  "websiteUrl": "https://linktr.ee/",
  "documentationUrl": "https://help.linktr.ee/collections/3020860-getting-started-with-linktree",
  "githubUrl": "https://github.com/search?q=linktree&type=repositories",
  "twitterUrl": null,
  "screenshot": "https://share.appsfor.us/screenshots/linktr_ee.png",
  "screenshot_640": "https://share.appsfor.us/screenshots/linktr_ee_640.png",
  "screenshot_400": "https://share.appsfor.us/screenshots/linktr_ee_400.png",
  "updatedAt": "2025-06-04T08:10:25.493Z"
}