{
  "sourceUrl": "https://manus.im/",
  "name": "Manus",
  "title": "manus.im",
  "payoff": "Community-driven task sharing platform",
  "shortDescription": "Manus is a platform where users can share tasks and projects, fostering a community-driven environment. It's designed for individuals interested in collaborative learning and project development. Users can contribute or pick up tasks, ranging from software development to educational content creation.",
  "pros": [
    "Encourages collaborative learning",
    "Wide range of project types",
    "User consent for content sharing"
  ],
  "cons": [
    "Depends on user contributions",
    "Limited moderation of content",
    "Potential for duplicated efforts"
  ],
  "alternatives": [
    "Trello [trello.com]",
    "Asana [asana.com]",
    "Basecamp [basecamp.com]"
  ],
  "aiSuggestedAlternatives": [
    {
      "name": "Slack",
      "url": "slack.com",
      "reason": "Enhances team communication"
    },
    {
      "name": "GitHub",
      "url": "github.com",
      "reason": "Supports collaborative coding"
    },
    {
      "name": "Monday.com",
      "url": "monday.com",
      "reason": "Flexible project management"
    }
  ],
  "tags": [
    "collaboration",
    "project management",
    "community",
    "task sharing"
  ],
  "apiUsed": false,
  "department": "Project Management Office",
  "function": "Project Tools",
  "freeTier": true,
  "openSource": false,
  "releasedYear": 2021,
  "websiteUrl": "https://manus.im/",
  "documentationUrl": null,
  "githubUrl": "https://github.com/search?q=manus&type=repositories",
  "twitterUrl": null,
  "screenshot": "/screenshots/manus_im.png",
  "screenshot_640": "/screenshots/manus_im_640.png",
  "screenshot_400": "/screenshots/manus_im_400.png",
  "updatedAt": "2025-06-02T03:08:19.962Z"
}