{
  "sourceUrl": "https://sink.cool/",
  "name": "Sink",
  "title": "sink.cool",
  "payoff": "Secure, Simple Link Shortener",
  "shortDescription": "Sink is a link shortening service designed for simplicity, speed, and security, fully hosted on Cloudflare. It compresses URLs to their minimal length, allowing users to monitor link analytics and gather insightful statistics. Ideal for marketers and content creators, Sink supports personalized slugs and case sensitivity, and allows setting expiration dates for links. An example use case is a marketing campaign where tracking link engagement is crucial.",
  "pros": [
    "100% run on Cloudflare for enhanced security",
    "Supports personalized slugs and case sensitivity",
    "Allows setting expiration dates for links"
  ],
  "cons": [
    "Limited customization options",
    "No mention of integration capabilities",
    "Potential privacy concerns with URL tracking"
  ],
  "alternatives": [
    "Bitly [bitly.com]",
    "TinyURL [tinyurl.com]",
    "Rebrandly [rebrandly.com]"
  ],
  "aiSuggestedAlternatives": [
    {
      "name": "Bitly",
      "url": "bitly.com",
      "reason": "Offers advanced link management"
    },
    {
      "name": "TinyURL",
      "url": "tinyurl.com",
      "reason": "Simple and widely recognized tool"
    },
    {
      "name": "Rebrandly",
      "url": "rebrandly.com",
      "reason": "Custom branding for links"
    }
  ],
  "tags": [
    "Link Shortener",
    "Analytics",
    "Cloudflare",
    "Security"
  ],
  "apiUsed": false,
  "department": "Marketing",
  "function": "Link Tools",
  "freeTier": true,
  "openSource": true,
  "releasedYear": 2021,
  "websiteUrl": "https://sink.cool/",
  "documentationUrl": null,
  "githubUrl": "https://github.com/ccbikai/sink",
  "twitterUrl": null,
  "screenshot": "https://share.appsfor.us/screenshots/sink_cool.png",
  "screenshot_640": "https://share.appsfor.us/screenshots/sink_cool_640.png",
  "screenshot_400": "https://share.appsfor.us/screenshots/sink_cool_400.png",
  "updatedAt": "2025-06-11T09:03:46.595Z"
}